zentropy/__init__.py
zentropy/ensemble.py
zentropy/lib.cpython-310-darwin.so
zentropy/utils.py
zentropy/version.py
zentropy/estimators/__init__.py
zentropy/estimators/continuous.py
zentropy/estimators/discrete.py
zentropy/estimators/mixed.py
zentropy/transforms/__init__.py
zentropy/transforms/knn_utils.py
zentropy/transforms/rank.py
zentropy-0.0.2.dist-info/METADATA
zentropy-0.0.2.dist-info/WHEEL
zentropy-0.0.2.dist-info/top_level.txt
zentropy-0.0.2.dist-info/RECORD
