Metadata-Version: 2.1
Name: zentropy
Version: 0.0.2
Summary: Nonparametric estimation of entropy and other information-theoretic quantities for continuous and categorical data
Author-email: Samuel Loomis <samlikesphysics@gmail.com>
Classifier: Programming Language :: Python :: 3
Classifier: License :: OSI Approved :: MIT License
Classifier: Operating System :: OS Independent
Requires-Python: >=3.10
